{
  "base": {
    "label": "Base",
    "metrics": {
      "pass_at_1": 0.2,
      "syntax_rate": 1.0,
      "hidden_pass_rate": 0.475,
      "format_compliance_rate": 1.0,
      "timeout_rate": 0.0,
      "repair_success_rate": 0.5125,
      "regression_rate": 0.475,
      "n_total": 120.0,
      "n_generation": 40.0,
      "n_repair": 80.0
    },
    "per_task_type": {
      "code_generation": {
        "total": 40,
        "passed": 8,
        "syntax_ok": 40,
        "format_ok": 40
      },
      "static_repair": {
        "total": 40,
        "passed": 22,
        "syntax_ok": 40,
        "format_ok": 40
      },
      "execution_repair": {
        "total": 40,
        "passed": 19,
        "syntax_ok": 40,
        "format_ok": 40
      }
    },
    "family_pass_count": 11,
    "family_total": 58
  },
  "stage1-code": {
    "label": "Stage1-Code",
    "metrics": {
      "pass_at_1": 0.125,
      "syntax_rate": 0.9666666666666667,
      "hidden_pass_rate": 0.38333333333333336,
      "format_compliance_rate": 0.9666666666666667,
      "timeout_rate": 0.041666666666666664,
      "repair_success_rate": 0.4375,
      "regression_rate": 0.5375,
      "n_total": 120.0,
      "n_generation": 40.0,
      "n_repair": 80.0
    },
    "per_task_type": {
      "code_generation": {
        "total": 40,
        "passed": 5,
        "syntax_ok": 40,
        "format_ok": 40
      },
      "static_repair": {
        "total": 40,
        "passed": 18,
        "syntax_ok": 39,
        "format_ok": 39
      },
      "execution_repair": {
        "total": 40,
        "passed": 17,
        "syntax_ok": 37,
        "format_ok": 37
      }
    },
    "family_pass_count": 8,
    "family_total": 58
  },
  "stage2-boundary": {
    "label": "Stage2-Boundary",
    "metrics": {
      "pass_at_1": 0.15,
      "syntax_rate": 0.9916666666666667,
      "hidden_pass_rate": 0.4666666666666667,
      "format_compliance_rate": 1.0,
      "timeout_rate": 0.06666666666666667,
      "repair_success_rate": 0.5375,
      "regression_rate": 0.4375,
      "n_total": 120.0,
      "n_generation": 40.0,
      "n_repair": 80.0
    },
    "per_task_type": {
      "code_generation": {
        "total": 40,
        "passed": 6,
        "syntax_ok": 40,
        "format_ok": 40
      },
      "static_repair": {
        "total": 40,
        "passed": 20,
        "syntax_ok": 39,
        "format_ok": 40
      },
      "execution_repair": {
        "total": 40,
        "passed": 23,
        "syntax_ok": 40,
        "format_ok": 40
      }
    },
    "family_pass_count": 12,
    "family_total": 58
  },
  "stage3-repair": {
    "label": "Stage3-Repair",
    "metrics": {
      "pass_at_1": 0.15,
      "syntax_rate": 0.9833333333333333,
      "hidden_pass_rate": 0.4583333333333333,
      "format_compliance_rate": 0.9833333333333333,
      "timeout_rate": 0.06666666666666667,
      "repair_success_rate": 0.525,
      "regression_rate": 0.4625,
      "n_total": 120.0,
      "n_generation": 40.0,
      "n_repair": 80.0
    },
    "per_task_type": {
      "code_generation": {
        "total": 40,
        "passed": 6,
        "syntax_ok": 38,
        "format_ok": 38
      },
      "static_repair": {
        "total": 40,
        "passed": 22,
        "syntax_ok": 40,
        "format_ok": 40
      },
      "execution_repair": {
        "total": 40,
        "passed": 20,
        "syntax_ok": 40,
        "format_ok": 40
      }
    },
    "family_pass_count": 13,
    "family_total": 58
  }
}